setup.py
engine_pin.egg-info/PKG-INFO
engine_pin.egg-info/SOURCES.txt
engine_pin.egg-info/dependency_links.txt
engine_pin.egg-info/requires.txt
engine_pin.egg-info/top_level.txt
pin/__init__.py
pin/router.py
pin/view.py
pin/embed/__init__.py
pin/embed/engine_simular_server.py
pin/embed/server.py
pin/kit/__init__.py
pin/kit/common.py
pin/kit/util.py
pin/kit/db/__init__.py
pin/kit/db/db.py
pin/kit/db/mysql.py
pin/kit/db/redis.py
pin/kit/rpc/__init__.py
pin/kit/rpc/servs.py
tests/__init__.py
tests/test_engine_server.py
tests/test_kit_store.py
tests/test_router.py
tests/test_server.py
tests/test_servs.py
tests/test_view.py
tests/token_mocker.py